{
    "version": "https://jsonfeed.org/version/1",
    "title": "Hexo • All posts by \"操作系统\" tag",
    "description": "",
    "home_page_url": "https://liuhuo23.github.io",
    "items": [
        {
            "id": "https://liuhuo23.github.io/2022/01/16/computer-science/%E6%93%8D%E4%BD%9C%E7%B3%BB%E7%BB%9F%E5%9F%BA%E6%9C%AC%E7%9F%A5%E8%AF%86/",
            "url": "https://liuhuo23.github.io/2022/01/16/computer-science/%E6%93%8D%E4%BD%9C%E7%B3%BB%E7%BB%9F%E5%9F%BA%E6%9C%AC%E7%9F%A5%E8%AF%86/",
            "title": "操作系统基本知识",
            "date_published": "2022-01-16T06:40:40.000Z",
            "content_html": "<h1 id=\"1-计算机基本知识总结\"><a class=\"anchor\" href=\"#1-计算机基本知识总结\">#</a> 1： 计算机基本知识总结</h1>\n<h2 id=\"1-计算机组成\"><a class=\"anchor\" href=\"#1-计算机组成\">#</a> 1. 计算机组成</h2>\n<blockquote>\n<p>一个完整的计算机系统，是由硬件系统与软件系统两大部分组成</p>\n</blockquote>\n<p><img data-src=\"https://raw.githubusercontent.com/liuhuo23/blog-img/main/img/1624895370503-aa65f8a4-261f-4555-afa5-53f3cbd92b23.png\" alt=\"image.png\"></p>\n<h2 id=\"11-硬件系统\"><a class=\"anchor\" href=\"#11-硬件系统\">#</a> 1.1： 硬件系统</h2>\n<p>计算机由运算器，存储器，控制器，输入输出设别这几个基本部分组成</p>\n<ol>\n<li>中央处理器</li>\n<li>负责数据的算数运算和逻辑运算，以及数据的加工处理，是整个计算机的核心。所有的硬件设备都是在中央处理器的控制下工作</li>\n<li>存储器\n<ol>\n<li>存储数据。分为： ROM 只读存储器，RAM 随机存储器俗称内存； 外存，包括硬盘，光盘，软盘等一切能够长久存储数据并能够被计算机读取的记忆设备</li>\n</ol>\n</li>\n<li>输入输出设备\n<ol>\n<li>输入设备： 泛指一切能够将信息转换为二进制数据并被电脑处理的设备，例如：键盘，听筒，摄像头</li>\n<li>输出设备： 泛指一切能够将二进制数据转换为非二进制信息的电子设备，例如：屏幕，喇叭</li>\n</ol>\n</li>\n</ol>\n<h2 id=\"12-软件系统\"><a class=\"anchor\" href=\"#12-软件系统\">#</a> 1.2： 软件系统</h2>\n<p>能实现特定功能的计算机指令集。包括，操作系统，数据库管理软件，驱动，应用软件</p>\n<h1 id=\"2-进制转换\"><a class=\"anchor\" href=\"#2-进制转换\">#</a> 2： 进制转换</h1>\n<blockquote>\n<p>计算机中所使用的只有二进制，为了表示与书写记忆的方便，人们提出了八进制，16 进制</p>\n</blockquote>\n<p><mark>注意：</mark> 不同进制只是对同一件事物的不同描述，本质上是一样的。</p>\n<h2 id=\"21-什么是进制\"><a class=\"anchor\" href=\"#21-什么是进制\">#</a> 2.1： 什么是进制</h2>\n<p>进制就是进位计数制，通俗的来说就是从右到左的数字代表的意义不同。例如： 十进制的 123，从右到左，3 代表 3 个，2 代表 20 个，1 代表一百个。分别是 10<sup>0</sup> ,10<sup>1</sup> ,10<sup>2</sup> .</p>\n<p>那么通过十进制我们可以不妨大胆假设，对于 N 进制来说（N&gt;=2）, 从右到左分别代表 N<sup>0</sup>,N<sup>1</sup> ,N<sup>2</sup> ,N<sup>n</sup> 。所遵循的原则都是逢 N 向高位进 1.</p>\n<h2 id=\"22-n进制转m进制\"><a class=\"anchor\" href=\"#22-n进制转m进制\">#</a> 2.2： N 进制转 M 进制</h2>\n<p>N 进制转 M 进制可以通过 10 进制作为中介进行转换。</p>\n<p>10 进制转 N 进制的方法是： 用 10 进制数一直除以 N，每一次结果保留余数，所得的商继续除以 N 直到最后的商小于 N。最后的商为最左边的数，剩下的余数从下到上按照从左到右的顺序列出，最后的结果即为 N 进制数</p>\n<p>N 进制转 10 进制数： 从右到左每一个数乘以它所在位的 N<sup>n</sup> , 最后把结果加起来就是。</p>\n<h1 id=\"3服务协议端口\"><a class=\"anchor\" href=\"#3服务协议端口\">#</a> 3: 服务，协议，端口</h1>\n<blockquote>\n<p>服务，协议，端口 。全世界的计算机正是通过他们为人类服务着</p>\n</blockquote>\n<h2 id=\"31常见的计算机服务\"><a class=\"anchor\" href=\"#31常见的计算机服务\">#</a> 3.1: 常见的计算机服务</h2>\n<p>计算机的服务是一种应用程序类型，这种程序没有 UI 界面。或者这种程序可以与有 UI 界面的程序发生交互。</p>\n<p>端口： 操作系统为了解决多个应用软件与一个 IP 之间的问题</p>\n<p>协议： 数据传输，解析所必须遵守的数据组织格式或者处理算法。</p>\n<h2 id=\"32-常见的计算服务协议端口的对应\"><a class=\"anchor\" href=\"#32-常见的计算服务协议端口的对应\">#</a> 3.2： 常见的计算服务，协议，端口的对应</h2>\n<p><img data-src=\"https://raw.githubusercontent.com/liuhuo23/blog-img/main/img/1623049782379-e00f6d3d-e5fa-40b5-8f0a-e21bf71ca778.png\" alt=\"协议端口\"></p>\n<h1 id=\"4dos命令\"><a class=\"anchor\" href=\"#4dos命令\">#</a> 4：DOS 命令</h1>\n<blockquote>\n<p>windows 常用 DOS 命</p>\n</blockquote>\n<h2 id=\"41-常见的dos命令\"><a class=\"anchor\" href=\"#41-常见的dos命令\">#</a> 4.1: 常见的 DOS 命令</h2>\n<ul>\n<li>\n<ul>\n<li><strong>gpedit.msc</strong>      // 组策略</li>\n<li><strong>lusrmgr.msc</strong>     // 本地用户和组</li>\n</ul>\n</li>\n<li>\n<ul>\n<li><strong>services.msc</strong>     // 本地服务设置</li>\n<li><strong>taskmgr</strong>          // 任务管理器</li>\n</ul>\n</li>\n<li>\n<ul>\n<li><strong>mmc</strong>              // 控制台</li>\n<li><strong>regedit</strong>          // 注册表编辑器</li>\n</ul>\n</li>\n<li>\n<ul>\n<li><strong>msconfig</strong>       // 系统配置（引导。服务。启动。工具）</li>\n<li><strong>mstsc</strong>            // 远程桌面</li>\n</ul>\n</li>\n<li>\n<ul>\n<li><strong>mspaint</strong>           // 画图</li>\n<li><strong>write</strong>             // 写字板</li>\n</ul>\n</li>\n<li>\n<ul>\n<li><strong>notepad</strong>         // 打开记事本</li>\n<li><strong>calc</strong>                // 打开计算器</li>\n</ul>\n</li>\n<li>\n<ul>\n<li><strong>explorer</strong>         // 打开文件资源管理器</li>\n<li><strong>logoff</strong>           // 注销命令</li>\n</ul>\n</li>\n<li>\n<ul>\n<li><strong>shutdown</strong>     //60 秒倒计时关机</li>\n</ul>\n</li>\n<li>\n<ul>\n<li><strong>ipconfig /all</strong>             // 查看网络详细信息</li>\n<li><strong>set</strong>                           // 显示当前所有环境变量</li>\n</ul>\n</li>\n<li>\n<ul>\n<li><strong>dir</strong>                           // 列出当前目录的文件</li>\n</ul>\n</li>\n<li>\n<ul>\n<li>\n<ul>\n<li><strong>dir  /a</strong>               // 列出所有文件包括隐藏文件</li>\n</ul>\n</li>\n</ul>\n</li>\n<li>\n<ul>\n<li><strong>whoami</strong>                    // 查看当前计算机名及当前用户名</li>\n<li><strong>tasklist</strong>                      // 列出当前所有服务的详细信息</li>\n</ul>\n</li>\n<li>\n<ul>\n<li>\n<ul>\n<li><strong>tasklist -svc</strong>       // 列出当前所有服务对应的 PID</li>\n</ul>\n</li>\n</ul>\n</li>\n<li>\n<ul>\n<li><strong>systeminfo</strong>               // 查看计算机详细信息</li>\n<li><strong>tree</strong>                         // 以树状的形式显示文件及文件夹</li>\n</ul>\n</li>\n<li>\n<ul>\n<li><strong>type 1.txt</strong>                 // 查看文件内容</li>\n<li><strong>start</strong>                        // 重新打开一个 cmd 窗口</li>\n</ul>\n</li>\n<li>\n<ul>\n<li>\n<ul>\n<li><strong>start 1.txt</strong>         <a href=\"//xn--1-xv6a93aw76bt2dz2i7n0aog5b.xn--txt-wu9dq54h\">// 使用记事本打开 1.txt 文件</a></li>\n</ul>\n</li>\n</ul>\n</li>\n<li>\n<ul>\n<li><strong>more 1.txt</strong>               // 分屏查看文本内容</li>\n<li><strong>arp -a</strong>                     // 查看网内主机</li>\n</ul>\n</li>\n<li>\n<ul>\n<li><strong>net user</strong>                 // 查看当前计算机所有用户</li>\n</ul>\n</li>\n<li>\n<ul>\n<li>\n<ul>\n<li><strong>net user as-before</strong>    // 查看指定用户属性</li>\n</ul>\n</li>\n</ul>\n</li>\n<li>\n<ul>\n<li><strong>net start</strong>                   // 查看启动的 windows 服务</li>\n</ul>\n</li>\n<li>\n<ul>\n<li>\n<ul>\n<li><strong>net start 迅雷下载基础服务（用于快速申请磁盘空间及接管浏览器下载请求）</strong></li>\n<li>**net stop 迅雷下载基础服务（用于快速申请磁盘空间及接管浏览器下载请求）**PS:(需要管理员权限)</li>\n</ul>\n</li>\n</ul>\n</li>\n<li>\n<ul>\n<li><strong>net view</strong>                   // 显示域列表、计算机列表或指定计算机的共享资源列表</li>\n</ul>\n</li>\n<li>\n<ul>\n<li>\n<ul>\n<li><strong>net view ip</strong>      // 显示指定的 ip 的共享资源列表</li>\n</ul>\n</li>\n</ul>\n</li>\n<li>\n<ul>\n<li><strong>net config</strong>               // 用于显示服务器的打开文件数量和空闲回话时间及用户登录数量</li>\n</ul>\n</li>\n<li>\n<ul>\n<li>\n<ul>\n<li><strong>net config Server</strong>      // 查看服务器的     PS:(运行需要管理员权限)</li>\n<li><strong>net config Workstation</strong>   // 查看当前工作站的    PS:(运行需要管理员权限)</li>\n</ul>\n</li>\n</ul>\n</li>\n<li>\n<ul>\n<li><strong>net share</strong>               // 查看本地开启的共享文件</li>\n<li><strong>netstat -an</strong>            // 查看开启的端口信息</li>\n</ul>\n</li>\n<li>\n<ul>\n<li>\n<ul>\n<li><strong>netstat -ano</strong>   // 查看带有 PID 的端口信息</li>\n</ul>\n</li>\n</ul>\n</li>\n<li>\n<ul>\n<li><strong>nslookup</strong>              // 查询 DNS 的记录，查询域名解析，用来诊断网络问题</li>\n<li><strong>tracert <span class=\"exturl\" data-url=\"aHR0cDovL3d3dy5iYWlkdS5jb20=\">www.baidu.com</span></strong>       // 路由追踪</li>\n</ul>\n</li>\n<li>\n<ul>\n<li><strong>ping</strong>                    // 测试网络连通</li>\n<li><strong>cd</strong>                       // 切换目录</li>\n</ul>\n</li>\n<li>\n<ul>\n<li>\n<ul>\n<li><strong>cd .</strong>             // 还在当前目录</li>\n<li><strong>cd ..</strong>            // 切换到上层目录</li>\n</ul>\n</li>\n</ul>\n</li>\n<li>\n<ul>\n<li>\n<ul>\n<li>*<em>cd *</em>             // 切换至根目录</li>\n<li><strong>cd . &gt; 1.txt</strong>    // 创建文件</li>\n</ul>\n</li>\n</ul>\n</li>\n<li>\n<ul>\n<li><strong>d：</strong>            // 直接跳转至 d 盘根目录</li>\n<li><strong>md test</strong>           // 创建 test 目录</li>\n</ul>\n</li>\n<li>\n<ul>\n<li><strong>rd test</strong>             // 删除 test 目录</li>\n</ul>\n</li>\n<li>\n<ul>\n<li>\n<ul>\n<li><strong>rd /s test</strong>         // 删除目录需要确定</li>\n</ul>\n</li>\n</ul>\n</li>\n<li>\n<ul>\n<li><strong>copy 1.txt 2.txt</strong>          <a href=\"//xn--1-lf8a13s.xn--txt2-dx8fl9ag06bzr4c.txt\">// 复制 1.txt 的内容到 2.txt</a>，如果 2.txt 存在内容会提示你是否覆盖</li>\n<li><strong>del 2.txt</strong>            // 删除文件</li>\n</ul>\n</li>\n<li>\n<ul>\n<li>\n<ul>\n<li><strong>del -f 1.txt</strong>            // 强制删除</li>\n</ul>\n</li>\n</ul>\n</li>\n<li>\n<ul>\n<li><strong>move 1.txt test</strong>        <a href=\"//xn--1-4i2b.xn--txttest-kg5kf4qyxbyxbsy0c7r0bh30d\">// 将 1.txt 移动到 test 文件夹内</a></li>\n<li><strong>move  1.txt 2.txt</strong>        <a href=\"//xn--1-4i2b.xn--txt2-xh5fn22anwa9819a.txt\">// 将 1.txt 重命名为 2.txt</a></li>\n</ul>\n</li>\n<li>\n<ul>\n<li><strong>ren 1.txt 2.txt</strong>             // 重命名</li>\n<li><strong>shutdown -s</strong>          // 一分钟后关机</li>\n</ul>\n</li>\n<li>\n<ul>\n<li>\n<ul>\n<li><strong>shutdown -s -t 100 -c \"bye\"</strong>     // 100 秒后关机并弹出 bye 消息</li>\n<li><strong>shutdown -a</strong>     // 取消计划的关机任务</li>\n</ul>\n</li>\n</ul>\n</li>\n<li>\n<ul>\n<li><strong>net use K: \\ip\\c$</strong>       // 映射目标 ip 的 c 盘到本地 k 盘</li>\n<li><strong>net use k: \\ip\\c$ \\del</strong>       // 删除映射的 k 盘</li>\n</ul>\n</li>\n<li>\n<ul>\n<li><strong>taskkill  /f /im xx.exe</strong>      // 强制终止某进程</li>\n<li><strong>findstr “Hello”aa.txt</strong>    <a href=\"//xn--aa-rl8c.xn--txthello-nd0mtb06mt40e5zb204b5mkph1g\">// 在 aa.txt 文件中寻找字符串 hello</a></li>\n</ul>\n</li>\n<li>\n<ul>\n<li><strong>echo hello » pass.txt</strong>      <a href=\"//xn--hellopass-9y4op2b060ejy3m.xn--txt-x68dy9al71g\">// 将 hello 追加到 pass.txt 文件中</a> (一个&gt; 直接覆盖原内容)</li>\n<li><strong>color 02</strong>     // 把 cmd 中的字改为绿色字体</li>\n</ul>\n</li>\n<li>\n<ul>\n<li></li>\n</ul>\n</li>\n</ul>\n",
            "tags": [
                "操作系统"
            ]
        }
    ]
}